[
  {
    "source_record_id": "permit-501",
    "house_number": "4000",
    "street_name": "PINE AVE NW",
    "permit_description": "Interior renovation for 3 bedroom 2 bathroom home",
    "source_name": "permit_file"
  },
  {
    "source_record_id": "permit-502",
    "house_number": "4001",
    "street_name": "PINE AVE NW",
    "permit_description": "Interior renovation for 3 bedroom 2 bathroom home",
    "source_name": "permit_file"
  },
  {
    "source_record_id": "permit-503",
    "house_number": "4002",
    "street_name": "PINE AVE NW",
    "permit_description": "Interior renovation for 3 bedroom 2 bathroom home",
    "source_name": "permit_file"
  },
  {
    "source_record_id": "permit-504",
    "house_number": "4003",
    "street_name": "PINE AVE NW",
    "permit_description": "Interior renovation for 3 bedroom 2 bathroom home",
    "source_name": "permit_file"
  },
  {
    "source_record_id": "permit-505",
    "house_number": "4004",
    "street_name": "PINE AVE NW",
    "permit_description": "Interior renovation for 3 bedroom 2 bathroom home",
    "source_name": "permit_file"
  },
  {
    "source_record_id": "permit-506",
    "house_number": "4005",
    "street_name": "PINE AVE NW",
    "permit_description": "Interior renovation for 3 bedroom 2 bathroom home",
    "source_name": "permit_file"
  },
  {
    "source_record_id": "permit-507",
    "house_number": "4006",
    "street_name": "PINE AVE NW",
    "permit_description": "Interior renovation for 3 bedroom 2 bathroom home",
    "source_name": "permit_file"
  },
  {
    "source_record_id": "permit-508",
    "house_number": "4007",
    "street_name": "PINE AVE NW",
    "permit_description": "Interior renovation for 3 bedroom 2 bathroom home",
    "source_name": "permit_file"
  },
  {
    "source_record_id": "permit-509",
    "house_number": "4008",
    "street_name": "PINE AVE NW",
    "permit_description": "Interior renovation for 3 bedroom 2 bathroom home",
    "source_name": "permit_file"
  },
  {
    "source_record_id": "permit-510",
    "house_number": "4009",
    "street_name": "PINE AVE NW",
    "permit_description": "Interior renovation for 3 bedroom 2 bathroom home",
    "source_name": "permit_file"
  },
  {
    "source_record_id": "permit-511",
    "house_number": "4010",
    "street_name": "PINE AVE NW",
    "permit_description": "Interior renovation for 3 bedroom 2 bathroom home",
    "source_name": "permit_file"
  },
  {
    "source_record_id": "permit-512",
    "house_number": "4011",
    "street_name": "PINE AVE NW",
    "permit_description": "Interior renovation for 3 bedroom 2 bathroom home",
    "source_name": "permit_file"
  },
  {
    "source_record_id": "permit-513",
    "house_number": "4012",
    "street_name": "PINE AVE NW",
    "permit_description": "Interior renovation for 3 bedroom 2 bathroom home",
    "source_name": "permit_file"
  },
  {
    "source_record_id": "permit-514",
    "house_number": "4013",
    "street_name": "PINE AVE NW",
    "permit_description": "Interior renovation for 3 bedroom 2 bathroom home",
    "source_name": "permit_file"
  },
  {
    "source_record_id": "permit-515",
    "house_number": "4014",
    "street_name": "PINE AVE NW",
    "permit_description": "Interior renovation for 3 bedroom 2 bathroom home",
    "source_name": "permit_file"
  },
  {
    "source_record_id": "permit-516",
    "house_number": "4015",
    "street_name": "PINE AVE NW",
    "permit_description": "Interior renovation for 3 bedroom 2 bathroom home",
    "source_name": "permit_file"
  },
  {
    "source_record_id": "permit-517",
    "house_number": "4016",
    "street_name": "PINE AVE NW",
    "permit_description": "Interior renovation for 3 bedroom 2 bathroom home",
    "source_name": "permit_file"
  },
  {
    "source_record_id": "permit-518",
    "house_number": "4017",
    "street_name": "PINE AVE NW",
    "permit_description": "Interior renovation for 3 bedroom 2 bathroom home",
    "source_name": "permit_file"
  },
  {
    "source_record_id": "permit-519",
    "house_number": "4018",
    "street_name": "PINE AVE NW",
    "permit_description": "Interior renovation for 3 bedroom 2 bathroom home",
    "source_name": "permit_file"
  },
  {
    "source_record_id": "permit-520",
    "house_number": "4019",
    "street_name": "PINE AVE NW",
    "permit_description": "Interior renovation for 3 bedroom 2 bathroom home",
    "source_name": "permit_file"
  },
  {
    "source_record_id": "permit-unmatched-0",
    "house_number": "9500",
    "street_name": "UNKNOWN AVE NW",
    "permit_description": "Development permit for 4 bedroom 3 bathroom dwelling",
    "source_name": "permit_file"
  },
  {
    "source_record_id": "permit-unmatched-1",
    "house_number": "9501",
    "street_name": "UNKNOWN AVE NW",
    "permit_description": "Development permit for 4 bedroom 3 bathroom dwelling",
    "source_name": "permit_file"
  },
  {
    "source_record_id": "permit-unmatched-2",
    "house_number": "9502",
    "street_name": "UNKNOWN AVE NW",
    "permit_description": "Development permit for 4 bedroom 3 bathroom dwelling",
    "source_name": "permit_file"
  },
  {
    "source_record_id": "permit-unmatched-3",
    "house_number": "9503",
    "street_name": "UNKNOWN AVE NW",
    "permit_description": "Development permit for 4 bedroom 3 bathroom dwelling",
    "source_name": "permit_file"
  },
  {
    "source_record_id": "permit-unmatched-4",
    "house_number": "9504",
    "street_name": "UNKNOWN AVE NW",
    "permit_description": "Development permit for 4 bedroom 3 bathroom dwelling",
    "source_name": "permit_file"
  },
  {
    "source_record_id": "permit-unmatched-5",
    "house_number": "9505",
    "street_name": "UNKNOWN AVE NW",
    "permit_description": "Development permit for 4 bedroom 3 bathroom dwelling",
    "source_name": "permit_file"
  },
  {
    "source_record_id": "permit-unmatched-6",
    "house_number": "9506",
    "street_name": "UNKNOWN AVE NW",
    "permit_description": "Development permit for 4 bedroom 3 bathroom dwelling",
    "source_name": "permit_file"
  },
  {
    "source_record_id": "permit-unmatched-7",
    "house_number": "9507",
    "street_name": "UNKNOWN AVE NW",
    "permit_description": "Development permit for 4 bedroom 3 bathroom dwelling",
    "source_name": "permit_file"
  },
  {
    "source_record_id": "permit-unmatched-8",
    "house_number": "9508",
    "street_name": "UNKNOWN AVE NW",
    "permit_description": "Development permit for 4 bedroom 3 bathroom dwelling",
    "source_name": "permit_file"
  },
  {
    "source_record_id": "permit-unmatched-9",
    "house_number": "9509",
    "street_name": "UNKNOWN AVE NW",
    "permit_description": "Development permit for 4 bedroom 3 bathroom dwelling",
    "source_name": "permit_file"
  }
]